
{
	"commands" : "",
	"description" : "Generated when this file was opened on 2023/08/26 12:28:42.",
	"label" : "auto base",
	"workbook_meta" : 
	{
		"_name" : "c:\\users\\smati\\google drive\\github\\repos\\sagirumati\\uroot package\\uroot\\uroot2a9078be41d8.wf1",
		"_pages" : 
		[
			
			{
				"_frequency" : "U",
				"_last_update" : [ 738757.4657175926, "26/08/2023 11:10" ],
				"_name" : "Untitled",
				"_obj_count" : 8,
				"_objects" : 
				[
					
					{
						"_data_type" : "integer",
						"_name" : "@DATE",
						"_obs_max" : 100,
						"_obs_min" : 1,
						"_type" : "INDEX"
					},
					
					{
						"_name" : "ADF_TABLE",
						"_type" : "TABLE"
					},
					
					{
						"_name" : "C",
						"_type" : "COEF"
					},
					
					{
						"_name" : "PP_TABLE",
						"_type" : "TABLE"
					},
					
					{
						"_name" : "RESID",
						"_type" : "SERIES"
					},
					
					{
						"_name" : "UNIT_ROOT_TEST_GROUP",
						"_type" : "GROUP"
					},
					
					{
						"_name" : "UNITROOT_RESULTS",
						"_type" : "SPOOL"
					},
					
					{
						"_name" : "X",
						"_type" : "SERIES"
					},
					
					{
						"_name" : "Y",
						"_type" : "SERIES"
					}
				],
				"_obs_count" : 100
			}
		]
	}
}
